MANIFEST.in
README.md
setup.py
prala/__init__.py
prala/accessories.py
prala/console.py
prala/core.py
prala/exceptions.py
prala/gui.py
prala/test_console.py
prala/test_core_01.py
prala/test_core_02.py
prala.egg-info/PKG-INFO
prala.egg-info/SOURCES.txt
prala.egg-info/dependency_links.txt
prala.egg-info/entry_points.txt
prala.egg-info/not-zip-safe
prala.egg-info/requires.txt
prala.egg-info/top_level.txt
prala/common/__init__.py
prala/common/common.py
prala/common/setup.ini
prala/images/empty-light.png
prala/images/enable-to-say-off-tool.png
prala/images/enable-to-say-on-tool.png
prala/images/enable-to-show-note-off-tool.png
prala/images/enable-to-show-note-on-tool.png
prala/images/enable-to-show-pattern-off-tool.png
prala/images/enable-to-show-pattern-on-tool.png
prala/images/green-light.png
prala/images/ok-button-focus.png
prala/images/ok-button-hover.png
prala/images/ok-button-pressed.png
prala/images/ok-button.png
prala/images/open-tool.png
prala/images/quit-tool.png
prala/images/red-light.png
prala/images/say-tool.png
prala/images/start-tool.png
prala/locales/en_US/LC_MESSAGES/prala.mo
prala/locales/hu_HU/LC_MESSAGES/prala.mo
prala/templates/template.dict